COSIPY.py
cosipy/__init__.py
cosipy/config.py
cosipy/constants.py
cosipy/cpkernel/__init__.py
cosipy/cpkernel/cosipy_core.py
cosipy/cpkernel/grid.py
cosipy/cpkernel/init.py
cosipy/cpkernel/io.py
cosipy/cpkernel/node.py
cosipy/modules/__init__.py
cosipy/modules/albedo.py
cosipy/modules/densification.py
cosipy/modules/evaluation.py
cosipy/modules/heatEquation.py
cosipy/modules/penetratingRadiation.py
cosipy/modules/percolation.py
cosipy/modules/radCor.py
cosipy/modules/refreezing.py
cosipy/modules/roughness.py
cosipy/modules/secant.py
cosipy/modules/surfaceTemperature.py
cosipy/postprocessing/__init__.py
cosipy/postprocessing/field_plots/README
cosipy/postprocessing/field_plots/__init__.py
cosipy/postprocessing/field_plots/plot_cosipy_fields.py
cosipy/postprocessing/profile_plots/__init__.py
cosipy/postprocessing/profile_plots/plot_profiles.py
cosipy/postprocessing/vtk_plots/README
cosipy/postprocessing/vtk_plots/__init__.py
cosipy/postprocessing/vtk_plots/plot_cosipy_fields_vtk.py
cosipy/tests/__init__.py
cosipy/tests/conftest.py
cosipy/tests/test_GRID_getter_functions.py
cosipy/tests/test_GRID_update_functions.py
cosipy/tests/test_NODE_getter_functions.py
cosipy/tests/test_NODE_setter_functions.py
cosipy/tests/test_config.py
cosipy/tests/test_parameterisation_albedo.py
cosipy/tests/test_parameterisation_densification.py
cosipy/tests/test_parameterisation_heatEquation.py
cosipy/tests/test_parameterisation_penetratingRadiation.py
cosipy/tests/test_parameterisation_percolation.py
cosipy/tests/test_parameterisation_refreezing.py
cosipy/tests/test_parameterisation_roughness.py
cosipy/tests/test_parameterisation_surfaceTemperature.py
cosipy/tests/test_postprocessing_field_plots.py
cosipy/tests/test_utilities_config.py
cosipy/utilities/__init__.py
cosipy/utilities/config_utils.py
cosipy/utilities/aws2cosipy/__init__.py
cosipy/utilities/aws2cosipy/aws2cosipy.py
cosipy/utilities/createStatic/__init__.py
cosipy/utilities/createStatic/create_static_file.py
cosipymodel-2.0.2.dist-info/METADATA
cosipymodel-2.0.2.dist-info/WHEEL
cosipymodel-2.0.2.dist-info/entry_points.txt
cosipymodel-2.0.2.dist-info/licenses/LICENSE
cosipymodel-2.0.2.dist-info/RECORD
