Metadata-Version: 2.3
Name: cosipymodel
Version: 2.0.2
Summary: Coupled snowpack and ice surface energy and mass balance model in Python.
Project-URL: Homepage, https://github.com/cryotools/cosipy
Project-URL: Bug Tracker, https://github.com/cryotools/cosipy/issues
Project-URL: Documentation, https://cosipy.readthedocs.io/en/latest/
Author: COSIPY Contributors
License: GPL-3.0
Keywords: energy balance model,glacier modelling,glaciers,glaciology,mass balance
Classifier: Development Status :: 5 - Production/Stable
Classifier: Environment :: Console
Classifier: Intended Audience :: Science/Research
Classifier: License :: OSI Approved :: GNU General Public License v3 (GPLv3)
Classifier: Operating System :: POSIX :: Linux
Classifier: Programming Language :: Python :: 3.9
Classifier: Programming Language :: Python :: 3.10
Classifier: Programming Language :: Python :: 3.11
Classifier: Programming Language :: Python :: 3.12
Classifier: Topic :: Scientific/Engineering :: Atmospheric Science
Classifier: Topic :: Scientific/Engineering :: Information Analysis
Requires-Python: >=3.9
Requires-Dist: cartopy
Requires-Dist: cdo
Requires-Dist: dask
Requires-Dist: dask-jobqueue
Requires-Dist: distributed; python_version > '3.11'
Requires-Dist: distributed<=2024.2.0; python_version < '3.11'
Requires-Dist: matplotlib
Requires-Dist: metpy
Requires-Dist: nco
Requires-Dist: netcdf4>=1.5.1.2
Requires-Dist: numba
Requires-Dist: numpy>=2.0
Requires-Dist: pandas>2.0
Requires-Dist: richdem; python_version < '3.11'
Requires-Dist: scipy>=1.1.0
Requires-Dist: tomli; python_version < '3.11'
Requires-Dist: vtk
Requires-Dist: xarray-spatial
Requires-Dist: xarray>=0.18.0
Provides-Extra: dev
Requires-Dist: black>=23.1; extra == 'dev'
Requires-Dist: build>=0.7; extra == 'dev'
Requires-Dist: codecov; extra == 'dev'
Requires-Dist: coveralls; extra == 'dev'
Requires-Dist: flake8>=6.0; extra == 'dev'
Requires-Dist: hatchling>=1.12; extra == 'dev'
Requires-Dist: isort; extra == 'dev'
Requires-Dist: pylint>=2.16.1; extra == 'dev'
Requires-Dist: pytest; extra == 'dev'
Requires-Dist: pytest-dependency; extra == 'dev'
Requires-Dist: sphinx; extra == 'dev'
Requires-Dist: sphinx-rtd-theme>=1.1; extra == 'dev'
Provides-Extra: docs
Requires-Dist: sphinx; extra == 'docs'
Requires-Dist: sphinx-rtd-theme>=1.1; extra == 'docs'
Provides-Extra: tests
Requires-Dist: codecov; extra == 'tests'
Requires-Dist: coveralls; extra == 'tests'
Requires-Dist: pytest; extra == 'tests'
Requires-Dist: pytest-dependency; extra == 'tests'
